setup.py
hpa_utils/hpa_utils.py
hpa_utils.egg-info/PKG-INFO
hpa_utils.egg-info/SOURCES.txt
hpa_utils.egg-info/dependency_links.txt
hpa_utils.egg-info/not-zip-safe
hpa_utils.egg-info/requires.txt
hpa_utils.egg-info/top_level.txt