Metadata-Version: 1.0
Name: hpa-utils
Version: 0.1
Summary: utilities for downloading and processing image data from nference Human Protein Atlas collection
Home-page: UNKNOWN
Author: Martin Kang
Author-email: martin@nference.net
License: UNKNOWN
Platform: UNKNOWN
